README.md
setup.py
SearchOverflow/__init__.py
SearchOverflow.egg-info/PKG-INFO
SearchOverflow.egg-info/SOURCES.txt
SearchOverflow.egg-info/dependency_links.txt
SearchOverflow.egg-info/entry_points.txt
SearchOverflow.egg-info/not-zip-safe
SearchOverflow.egg-info/requires.txt
SearchOverflow.egg-info/top_level.txt