Metadata-Version: 2.1
Name: SearchOverflow
Version: 1.0.1
Summary: Script to make searches on StackOverflow
Home-page: https://aiherroc.upv.edu.es
Author: Airam Hernández Rocha
Author-email: airamhr7@gmail.com
License: Apache License 2.0
Keywords: StackOverflow code search python java stackoverflow
Platform: UNKNOWN
Classifier: Programming Language :: Python :: 3
Classifier: License :: OSI Approved :: Apache Software License
Classifier: Operating System :: OS Independent
